jorgesomas3/__init__.py
jorgesomas3/soma.py
jorgesomas3-0.1.dist-info/LICENSE
jorgesomas3-0.1.dist-info/METADATA
jorgesomas3-0.1.dist-info/WHEEL
jorgesomas3-0.1.dist-info/top_level.txt
jorgesomas3-0.1.dist-info/RECORD
